code_to_text/__init__.py
code_to_text/code_to_text.py
tests/__init__.py
tests/test_code_to_text.py
easy_code_to_text-0.1.6.dist-info/LICENSE
easy_code_to_text-0.1.6.dist-info/METADATA
easy_code_to_text-0.1.6.dist-info/WHEEL
easy_code_to_text-0.1.6.dist-info/top_level.txt
easy_code_to_text-0.1.6.dist-info/RECORD
