Metadata-Version: 2.1
Name: easy-code-to-text
Version: 0.1.6
Summary: A Python package to concatenate code files into a single text file.
Home-page: https://github.com/Benalieur/EASY_CODE_TO_TEXT.git
Author: Benjamin QUINET
Author-email: benjamin.quinet59b@gmail.com
License: UNKNOWN
Platform: UNKNOWN
License-File: LICENSE
